ai_isometric_extractor/__init__.py
ai_isometric_extractor/anomaly.keras
ai_isometric_extractor/best.pt
ai_isometric_extractor/main.py
ai_isometric_extractor/my_model_keras.keras
ai_isometric_extractor-0.1.2.dist-info/METADATA
ai_isometric_extractor-0.1.2.dist-info/WHEEL
ai_isometric_extractor-0.1.2.dist-info/top_level.txt
ai_isometric_extractor-0.1.2.dist-info/RECORD
