Metadata-Version: 2.4
Name: ai-isometric-extractor
Version: 0.1.2
Summary: YOLOv8 + Keras based isometric diagram extraction
Author-email: Nabeel Ahmed Khan <nbeel.original@gmail.com>
Requires-Python: >=3.8
Requires-Dist: ultralytics
Requires-Dist: tensorflow
Requires-Dist: numpy
Requires-Dist: opencv-python
Requires-Dist: matplotlib
